{"size":{"code":"<span class=\"token tag\"><span class=\"token tag\"><span class=\"token punctuation\">&lt;</span>script</span><span class=\"token punctuation\">></span></span><span class=\"token script\"><span class=\"token language-javascript\">\n  <span class=\"token keyword\">import</span> Avatar <span class=\"token keyword\">from</span> <span class=\"token string\">'svelte-materialify/src/components/Avatar'</span><span class=\"token punctuation\">;</span>\n</span></span><span class=\"token tag\"><span class=\"token tag\"><span class=\"token punctuation\">&lt;/</span>script</span><span class=\"token punctuation\">></span></span>\n\n<span class=\"token tag\"><span class=\"token tag\"><span class=\"token punctuation\">&lt;</span>div</span> <span class=\"token attr-name\">class</span><span class=\"token attr-value\"><span class=\"token punctuation attr-equals\">=</span><span class=\"token punctuation\">\"</span>d-flex justify-space-around<span class=\"token punctuation\">\"</span></span><span class=\"token punctuation\">></span></span>\n  <span class=\"token tag\"><span class=\"token tag\"><span class=\"token punctuation\">&lt;</span>Avatar</span> <span class=\"token attr-name\">size</span><span class=\"token attr-value\"><span class=\"token punctuation attr-equals\">=</span><span class=\"token punctuation\">\"</span>36px<span class=\"token punctuation\">\"</span></span> <span class=\"token attr-name\">class</span><span class=\"token attr-value\"><span class=\"token punctuation attr-equals\">=</span><span class=\"token punctuation\">\"</span>primary-color<span class=\"token punctuation\">\"</span></span><span class=\"token punctuation\">></span></span>36<span class=\"token tag\"><span class=\"token tag\"><span class=\"token punctuation\">&lt;/</span>Avatar</span><span class=\"token punctuation\">></span></span>\n  <span class=\"token tag\"><span class=\"token tag\"><span class=\"token punctuation\">&lt;</span>Avatar</span> <span class=\"token attr-name\">class</span><span class=\"token attr-value\"><span class=\"token punctuation attr-equals\">=</span><span class=\"token punctuation\">\"</span>blue white-text<span class=\"token punctuation\">\"</span></span><span class=\"token punctuation\">></span></span>48<span class=\"token tag\"><span class=\"token tag\"><span class=\"token punctuation\">&lt;/</span>Avatar</span><span class=\"token punctuation\">></span></span>\n  <span class=\"token tag\"><span class=\"token tag\"><span class=\"token punctuation\">&lt;</span>Avatar</span> <span class=\"token attr-name\">size</span><span class=\"token attr-value\"><span class=\"token punctuation attr-equals\">=</span><span class=\"token punctuation\">\"</span>62px<span class=\"token punctuation\">\"</span></span> <span class=\"token attr-name\">class</span><span class=\"token attr-value\"><span class=\"token punctuation attr-equals\">=</span><span class=\"token punctuation\">\"</span>red white-text<span class=\"token punctuation\">\"</span></span><span class=\"token punctuation\">></span></span>62<span class=\"token tag\"><span class=\"token tag\"><span class=\"token punctuation\">&lt;/</span>Avatar</span><span class=\"token punctuation\">></span></span>\n<span class=\"token tag\"><span class=\"token tag\"><span class=\"token punctuation\">&lt;/</span>div</span><span class=\"token punctuation\">></span></span>\n","path":"examples/components/avatars/size.svelte"},"tile":{"code":"<span class=\"token tag\"><span class=\"token tag\"><span class=\"token punctuation\">&lt;</span>script</span><span class=\"token punctuation\">></span></span><span class=\"token script\"><span class=\"token language-javascript\">\n  <span class=\"token keyword\">import</span> Avatar <span class=\"token keyword\">from</span> <span class=\"token string\">'svelte-materialify/src/components/Avatar'</span><span class=\"token punctuation\">;</span>\n</span></span><span class=\"token tag\"><span class=\"token tag\"><span class=\"token punctuation\">&lt;/</span>script</span><span class=\"token punctuation\">></span></span>\n\n<span class=\"token tag\"><span class=\"token tag\"><span class=\"token punctuation\">&lt;</span>div</span> <span class=\"token attr-name\">class</span><span class=\"token attr-value\"><span class=\"token punctuation attr-equals\">=</span><span class=\"token punctuation\">\"</span>d-flex justify-center<span class=\"token punctuation\">\"</span></span><span class=\"token punctuation\">></span></span>\n  <span class=\"token tag\"><span class=\"token tag\"><span class=\"token punctuation\">&lt;</span>Avatar</span> <span class=\"token attr-name\">tile</span> <span class=\"token attr-name\">class</span><span class=\"token attr-value\"><span class=\"token punctuation attr-equals\">=</span><span class=\"token punctuation\">\"</span>blue white-text<span class=\"token punctuation\">\"</span></span><span class=\"token punctuation\">></span></span>TILE<span class=\"token tag\"><span class=\"token tag\"><span class=\"token punctuation\">&lt;/</span>Avatar</span><span class=\"token punctuation\">></span></span>\n<span class=\"token tag\"><span class=\"token tag\"><span class=\"token punctuation\">&lt;/</span>div</span><span class=\"token punctuation\">></span></span>\n","path":"examples/components/avatars/tile.svelte"},"types":{"code":"<span class=\"token tag\"><span class=\"token tag\"><span class=\"token punctuation\">&lt;</span>script</span><span class=\"token punctuation\">></span></span><span class=\"token script\"><span class=\"token language-javascript\">\n  <span class=\"token keyword\">import</span> Avatar <span class=\"token keyword\">from</span> <span class=\"token string\">'svelte-materialify/src/components/Avatar'</span><span class=\"token punctuation\">;</span>\n  <span class=\"token keyword\">import</span> Icon <span class=\"token keyword\">from</span> <span class=\"token string\">'svelte-materialify/src/components/Icon'</span><span class=\"token punctuation\">;</span>\n</span></span><span class=\"token tag\"><span class=\"token tag\"><span class=\"token punctuation\">&lt;/</span>script</span><span class=\"token punctuation\">></span></span>\n\n<span class=\"token tag\"><span class=\"token tag\"><span class=\"token punctuation\">&lt;</span>div</span> <span class=\"token attr-name\">class</span><span class=\"token attr-value\"><span class=\"token punctuation attr-equals\">=</span><span class=\"token punctuation\">\"</span>d-flex justify-space-around<span class=\"token punctuation\">\"</span></span><span class=\"token punctuation\">></span></span>\n  <span class=\"token tag\"><span class=\"token tag\"><span class=\"token punctuation\">&lt;</span>Avatar</span> <span class=\"token attr-name\">class</span><span class=\"token attr-value\"><span class=\"token punctuation attr-equals\">=</span><span class=\"token punctuation\">\"</span>primary-color<span class=\"token punctuation\">\"</span></span><span class=\"token punctuation\">></span></span>\n    <span class=\"token tag\"><span class=\"token tag\"><span class=\"token punctuation\">&lt;</span>Icon</span> <span class=\"token attr-name\">class</span><span class=\"token attr-value\"><span class=\"token punctuation attr-equals\">=</span><span class=\"token punctuation\">\"</span>mdi mdi-account-circle<span class=\"token punctuation\">\"</span></span> <span class=\"token punctuation\">/></span></span>\n  <span class=\"token tag\"><span class=\"token tag\"><span class=\"token punctuation\">&lt;/</span>Avatar</span><span class=\"token punctuation\">></span></span>\n  <span class=\"token tag\"><span class=\"token tag\"><span class=\"token punctuation\">&lt;</span>Avatar</span><span class=\"token punctuation\">></span></span><span class=\"token tag\"><span class=\"token tag\"><span class=\"token punctuation\">&lt;</span>img</span> <span class=\"token attr-name\">src</span><span class=\"token attr-value\"><span class=\"token punctuation attr-equals\">=</span><span class=\"token punctuation\">\"</span>https://picsum.photos/200<span class=\"token punctuation\">\"</span></span> <span class=\"token attr-name\">alt</span><span class=\"token attr-value\"><span class=\"token punctuation attr-equals\">=</span><span class=\"token punctuation\">\"</span>Avatar<span class=\"token punctuation\">\"</span></span> <span class=\"token punctuation\">/></span></span><span class=\"token tag\"><span class=\"token tag\"><span class=\"token punctuation\">&lt;/</span>Avatar</span><span class=\"token punctuation\">></span></span>\n  <span class=\"token tag\"><span class=\"token tag\"><span class=\"token punctuation\">&lt;</span>Avatar</span> <span class=\"token attr-name\">class</span><span class=\"token attr-value\"><span class=\"token punctuation attr-equals\">=</span><span class=\"token punctuation\">\"</span>red white-text<span class=\"token punctuation\">\"</span></span><span class=\"token punctuation\">></span></span><span class=\"token tag\"><span class=\"token tag\"><span class=\"token punctuation\">&lt;</span>b</span><span class=\"token punctuation\">></span></span>MS<span class=\"token tag\"><span class=\"token tag\"><span class=\"token punctuation\">&lt;/</span>b</span><span class=\"token punctuation\">></span></span><span class=\"token tag\"><span class=\"token tag\"><span class=\"token punctuation\">&lt;/</span>Avatar</span><span class=\"token punctuation\">></span></span>\n<span class=\"token tag\"><span class=\"token tag\"><span class=\"token punctuation\">&lt;/</span>div</span><span class=\"token punctuation\">></span></span>\n","path":"examples/components/avatars/types.svelte"}}