{"block":{"code":"<span class=\"token tag\"><span class=\"token tag\"><span class=\"token punctuation\">&lt;</span>script</span><span class=\"token punctuation\">></span></span><span class=\"token script\"><span class=\"token language-javascript\">\n  <span class=\"token keyword\">import</span> Button <span class=\"token keyword\">from</span> <span class=\"token string\">'svelte-materialify/src/components/Button'</span><span class=\"token punctuation\">;</span>\n</span></span><span class=\"token tag\"><span class=\"token tag\"><span class=\"token punctuation\">&lt;/</span>script</span><span class=\"token punctuation\">></span></span>\n\n<span class=\"token tag\"><span class=\"token tag\"><span class=\"token punctuation\">&lt;</span>Button</span> <span class=\"token attr-name\">block</span><span class=\"token punctuation\">></span></span>Block<span class=\"token tag\"><span class=\"token tag\"><span class=\"token punctuation\">&lt;/</span>Button</span><span class=\"token punctuation\">></span></span>\n","path":"examples/components/buttons/block.svelte"},"depressed":{"code":"<span class=\"token tag\"><span class=\"token tag\"><span class=\"token punctuation\">&lt;</span>script</span><span class=\"token punctuation\">></span></span><span class=\"token script\"><span class=\"token language-javascript\">\n  <span class=\"token keyword\">import</span> Button <span class=\"token keyword\">from</span> <span class=\"token string\">'svelte-materialify/src/components/Button'</span><span class=\"token punctuation\">;</span>\n</span></span><span class=\"token tag\"><span class=\"token tag\"><span class=\"token punctuation\">&lt;/</span>script</span><span class=\"token punctuation\">></span></span>\n\n<span class=\"token tag\"><span class=\"token tag\"><span class=\"token punctuation\">&lt;</span>div</span> <span class=\"token attr-name\">class</span><span class=\"token attr-value\"><span class=\"token punctuation attr-equals\">=</span><span class=\"token punctuation\">\"</span>d-flex flex-column flex-sm-row justify-space-between<span class=\"token punctuation\">\"</span></span><span class=\"token punctuation\">></span></span>\n  <span class=\"token tag\"><span class=\"token tag\"><span class=\"token punctuation\">&lt;</span>Button</span> <span class=\"token attr-name\">depressed</span><span class=\"token punctuation\">></span></span>Default<span class=\"token tag\"><span class=\"token tag\"><span class=\"token punctuation\">&lt;/</span>Button</span><span class=\"token punctuation\">></span></span>\n  <span class=\"token tag\"><span class=\"token tag\"><span class=\"token punctuation\">&lt;</span>Button</span> <span class=\"token attr-name\">depressed</span> <span class=\"token attr-name\">class</span><span class=\"token attr-value\"><span class=\"token punctuation attr-equals\">=</span><span class=\"token punctuation\">\"</span>red white-text<span class=\"token punctuation\">\"</span></span><span class=\"token punctuation\">></span></span>Red<span class=\"token tag\"><span class=\"token tag\"><span class=\"token punctuation\">&lt;/</span>Button</span><span class=\"token punctuation\">></span></span>\n  <span class=\"token tag\"><span class=\"token tag\"><span class=\"token punctuation\">&lt;</span>Button</span> <span class=\"token attr-name\">depressed</span> <span class=\"token attr-name\">class</span><span class=\"token attr-value\"><span class=\"token punctuation attr-equals\">=</span><span class=\"token punctuation\">\"</span>primary-color<span class=\"token punctuation\">\"</span></span><span class=\"token punctuation\">></span></span>Primary<span class=\"token tag\"><span class=\"token tag\"><span class=\"token punctuation\">&lt;/</span>Button</span><span class=\"token punctuation\">></span></span>\n  <span class=\"token tag\"><span class=\"token tag\"><span class=\"token punctuation\">&lt;</span>Button</span> <span class=\"token attr-name\">depressed</span> <span class=\"token attr-name\">disabled</span><span class=\"token punctuation\">></span></span>Disabled<span class=\"token tag\"><span class=\"token tag\"><span class=\"token punctuation\">&lt;/</span>Button</span><span class=\"token punctuation\">></span></span>\n<span class=\"token tag\"><span class=\"token tag\"><span class=\"token punctuation\">&lt;/</span>div</span><span class=\"token punctuation\">></span></span>\n","path":"examples/components/buttons/depressed.svelte"},"fab":{"code":"<span class=\"token tag\"><span class=\"token tag\"><span class=\"token punctuation\">&lt;</span>script</span><span class=\"token punctuation\">></span></span><span class=\"token script\"><span class=\"token language-javascript\">\n  <span class=\"token keyword\">import</span> Button <span class=\"token keyword\">from</span> <span class=\"token string\">'svelte-materialify/src/components/Button'</span><span class=\"token punctuation\">;</span>\n  <span class=\"token keyword\">import</span> Icon <span class=\"token keyword\">from</span> <span class=\"token string\">'svelte-materialify/src/components/Icon'</span><span class=\"token punctuation\">;</span>\n</span></span><span class=\"token tag\"><span class=\"token tag\"><span class=\"token punctuation\">&lt;/</span>script</span><span class=\"token punctuation\">></span></span>\n\n<span class=\"token tag\"><span class=\"token tag\"><span class=\"token punctuation\">&lt;</span>div</span> <span class=\"token attr-name\">class</span><span class=\"token attr-value\"><span class=\"token punctuation attr-equals\">=</span><span class=\"token punctuation\">\"</span>text-center<span class=\"token punctuation\">\"</span></span><span class=\"token punctuation\">></span></span>\n  <span class=\"token tag\"><span class=\"token tag\"><span class=\"token punctuation\">&lt;</span>Button</span> <span class=\"token attr-name\">fab</span><span class=\"token punctuation\">></span></span>\n    <span class=\"token tag\"><span class=\"token tag\"><span class=\"token punctuation\">&lt;</span>Icon</span> <span class=\"token attr-name\">class</span><span class=\"token attr-value\"><span class=\"token punctuation attr-equals\">=</span><span class=\"token punctuation\">\"</span>mdi mdi-home<span class=\"token punctuation\">\"</span></span> <span class=\"token punctuation\">/></span></span>\n  <span class=\"token tag\"><span class=\"token tag\"><span class=\"token punctuation\">&lt;/</span>Button</span><span class=\"token punctuation\">></span></span>\n  <span class=\"token tag\"><span class=\"token tag\"><span class=\"token punctuation\">&lt;</span>Button</span> <span class=\"token attr-name\">fab</span> <span class=\"token attr-name\">class</span><span class=\"token attr-value\"><span class=\"token punctuation attr-equals\">=</span><span class=\"token punctuation\">\"</span>red white-text<span class=\"token punctuation\">\"</span></span><span class=\"token punctuation\">></span></span>\n    <span class=\"token tag\"><span class=\"token tag\"><span class=\"token punctuation\">&lt;</span>Icon</span> <span class=\"token attr-name\">class</span><span class=\"token attr-value\"><span class=\"token punctuation attr-equals\">=</span><span class=\"token punctuation\">\"</span>mdi mdi-alert<span class=\"token punctuation\">\"</span></span> <span class=\"token punctuation\">/></span></span>\n  <span class=\"token tag\"><span class=\"token tag\"><span class=\"token punctuation\">&lt;/</span>Button</span><span class=\"token punctuation\">></span></span>\n  <span class=\"token tag\"><span class=\"token tag\"><span class=\"token punctuation\">&lt;</span>Button</span> <span class=\"token attr-name\">fab</span> <span class=\"token attr-name\">size</span><span class=\"token attr-value\"><span class=\"token punctuation attr-equals\">=</span><span class=\"token punctuation\">\"</span>small<span class=\"token punctuation\">\"</span></span> <span class=\"token attr-name\">class</span><span class=\"token attr-value\"><span class=\"token punctuation attr-equals\">=</span><span class=\"token punctuation\">\"</span>green white-text<span class=\"token punctuation\">\"</span></span><span class=\"token punctuation\">></span></span>\n    <span class=\"token tag\"><span class=\"token tag\"><span class=\"token punctuation\">&lt;</span>Icon</span> <span class=\"token attr-name\">class</span><span class=\"token attr-value\"><span class=\"token punctuation attr-equals\">=</span><span class=\"token punctuation\">\"</span>mdi mdi-pen<span class=\"token punctuation\">\"</span></span> <span class=\"token punctuation\">/></span></span>\n  <span class=\"token tag\"><span class=\"token tag\"><span class=\"token punctuation\">&lt;/</span>Button</span><span class=\"token punctuation\">></span></span>\n  <span class=\"token tag\"><span class=\"token tag\"><span class=\"token punctuation\">&lt;</span>Button</span> <span class=\"token attr-name\">fab</span> <span class=\"token attr-name\">size</span><span class=\"token attr-value\"><span class=\"token punctuation attr-equals\">=</span><span class=\"token punctuation\">\"</span>large<span class=\"token punctuation\">\"</span></span> <span class=\"token attr-name\">class</span><span class=\"token attr-value\"><span class=\"token punctuation attr-equals\">=</span><span class=\"token punctuation\">\"</span>blue white-text<span class=\"token punctuation\">\"</span></span><span class=\"token punctuation\">></span></span>\n    <span class=\"token tag\"><span class=\"token tag\"><span class=\"token punctuation\">&lt;</span>Icon</span> <span class=\"token attr-name\">class</span><span class=\"token attr-value\"><span class=\"token punctuation attr-equals\">=</span><span class=\"token punctuation\">\"</span>mdi mdi-cloud<span class=\"token punctuation\">\"</span></span> <span class=\"token punctuation\">/></span></span>\n  <span class=\"token tag\"><span class=\"token tag\"><span class=\"token punctuation\">&lt;/</span>Button</span><span class=\"token punctuation\">></span></span>\n<span class=\"token tag\"><span class=\"token tag\"><span class=\"token punctuation\">&lt;/</span>div</span><span class=\"token punctuation\">></span></span>\n","path":"examples/components/buttons/fab.svelte"},"icon":{"code":"<span class=\"token tag\"><span class=\"token tag\"><span class=\"token punctuation\">&lt;</span>script</span><span class=\"token punctuation\">></span></span><span class=\"token script\"><span class=\"token language-javascript\">\n  <span class=\"token keyword\">import</span> Button <span class=\"token keyword\">from</span> <span class=\"token string\">'svelte-materialify/src/components/Button'</span><span class=\"token punctuation\">;</span>\n  <span class=\"token keyword\">import</span> Icon <span class=\"token keyword\">from</span> <span class=\"token string\">'svelte-materialify/src/components/Icon'</span><span class=\"token punctuation\">;</span>\n</span></span><span class=\"token tag\"><span class=\"token tag\"><span class=\"token punctuation\">&lt;/</span>script</span><span class=\"token punctuation\">></span></span>\n\n<span class=\"token tag\"><span class=\"token tag\"><span class=\"token punctuation\">&lt;</span>div</span> <span class=\"token attr-name\">class</span><span class=\"token attr-value\"><span class=\"token punctuation attr-equals\">=</span><span class=\"token punctuation\">\"</span>d-flex flex-column flex-sm-row justify-space-around<span class=\"token punctuation\">\"</span></span><span class=\"token punctuation\">></span></span>\n  <span class=\"token tag\"><span class=\"token tag\"><span class=\"token punctuation\">&lt;</span>Button</span> <span class=\"token attr-name\">icon</span> <span class=\"token attr-name\">class</span><span class=\"token attr-value\"><span class=\"token punctuation attr-equals\">=</span><span class=\"token punctuation\">\"</span>pink-text<span class=\"token punctuation\">\"</span></span><span class=\"token punctuation\">></span></span>\n    <span class=\"token tag\"><span class=\"token tag\"><span class=\"token punctuation\">&lt;</span>Icon</span> <span class=\"token attr-name\">class</span><span class=\"token attr-value\"><span class=\"token punctuation attr-equals\">=</span><span class=\"token punctuation\">\"</span>mdi mdi-heart<span class=\"token punctuation\">\"</span></span> <span class=\"token punctuation\">/></span></span>\n  <span class=\"token tag\"><span class=\"token tag\"><span class=\"token punctuation\">&lt;/</span>Button</span><span class=\"token punctuation\">></span></span>\n  <span class=\"token tag\"><span class=\"token tag\"><span class=\"token punctuation\">&lt;</span>Button</span> <span class=\"token attr-name\">icon</span> <span class=\"token attr-name\">class</span><span class=\"token attr-value\"><span class=\"token punctuation attr-equals\">=</span><span class=\"token punctuation\">\"</span>indigo-text<span class=\"token punctuation\">\"</span></span><span class=\"token punctuation\">></span></span>\n    <span class=\"token tag\"><span class=\"token tag\"><span class=\"token punctuation\">&lt;</span>Icon</span> <span class=\"token attr-name\">class</span><span class=\"token attr-value\"><span class=\"token punctuation attr-equals\">=</span><span class=\"token punctuation\">\"</span>mdi mdi-star<span class=\"token punctuation\">\"</span></span> <span class=\"token punctuation\">/></span></span>\n  <span class=\"token tag\"><span class=\"token tag\"><span class=\"token punctuation\">&lt;/</span>Button</span><span class=\"token punctuation\">></span></span>\n  <span class=\"token tag\"><span class=\"token tag\"><span class=\"token punctuation\">&lt;</span>Button</span> <span class=\"token attr-name\">icon</span> <span class=\"token attr-name\">class</span><span class=\"token attr-value\"><span class=\"token punctuation attr-equals\">=</span><span class=\"token punctuation\">\"</span>green-text<span class=\"token punctuation\">\"</span></span><span class=\"token punctuation\">></span></span>\n    <span class=\"token tag\"><span class=\"token tag\"><span class=\"token punctuation\">&lt;</span>Icon</span> <span class=\"token attr-name\">class</span><span class=\"token attr-value\"><span class=\"token punctuation attr-equals\">=</span><span class=\"token punctuation\">\"</span>mdi mdi-thumb-up<span class=\"token punctuation\">\"</span></span> <span class=\"token punctuation\">/></span></span>\n  <span class=\"token tag\"><span class=\"token tag\"><span class=\"token punctuation\">&lt;/</span>Button</span><span class=\"token punctuation\">></span></span>\n  <span class=\"token tag\"><span class=\"token tag\"><span class=\"token punctuation\">&lt;</span>Button</span> <span class=\"token attr-name\">icon</span> <span class=\"token attr-name\">disabled</span><span class=\"token punctuation\">></span></span>\n    <span class=\"token tag\"><span class=\"token tag\"><span class=\"token punctuation\">&lt;</span>Icon</span> <span class=\"token attr-name\">class</span><span class=\"token attr-value\"><span class=\"token punctuation attr-equals\">=</span><span class=\"token punctuation\">\"</span>mdi mdi-cancel<span class=\"token punctuation\">\"</span></span> <span class=\"token punctuation\">/></span></span>\n  <span class=\"token tag\"><span class=\"token tag\"><span class=\"token punctuation\">&lt;/</span>Button</span><span class=\"token punctuation\">></span></span>\n<span class=\"token tag\"><span class=\"token tag\"><span class=\"token punctuation\">&lt;/</span>div</span><span class=\"token punctuation\">></span></span>\n","path":"examples/components/buttons/icon.svelte"},"outlined":{"code":"<span class=\"token tag\"><span class=\"token tag\"><span class=\"token punctuation\">&lt;</span>script</span><span class=\"token punctuation\">></span></span><span class=\"token script\"><span class=\"token language-javascript\">\n  <span class=\"token keyword\">import</span> Button <span class=\"token keyword\">from</span> <span class=\"token string\">'svelte-materialify/src/components/Button'</span><span class=\"token punctuation\">;</span>\n</span></span><span class=\"token tag\"><span class=\"token tag\"><span class=\"token punctuation\">&lt;/</span>script</span><span class=\"token punctuation\">></span></span>\n\n<span class=\"token tag\"><span class=\"token tag\"><span class=\"token punctuation\">&lt;</span>div</span> <span class=\"token attr-name\">class</span><span class=\"token attr-value\"><span class=\"token punctuation attr-equals\">=</span><span class=\"token punctuation\">\"</span>d-flex flex-column flex-sm-row justify-space-between<span class=\"token punctuation\">\"</span></span><span class=\"token punctuation\">></span></span>\n  <span class=\"token tag\"><span class=\"token tag\"><span class=\"token punctuation\">&lt;</span>Button</span> <span class=\"token attr-name\">outlined</span><span class=\"token punctuation\">></span></span>Default<span class=\"token tag\"><span class=\"token tag\"><span class=\"token punctuation\">&lt;/</span>Button</span><span class=\"token punctuation\">></span></span>\n  <span class=\"token tag\"><span class=\"token tag\"><span class=\"token punctuation\">&lt;</span>Button</span> <span class=\"token attr-name\">outlined</span> <span class=\"token attr-name\">class</span><span class=\"token attr-value\"><span class=\"token punctuation attr-equals\">=</span><span class=\"token punctuation\">\"</span>red-text<span class=\"token punctuation\">\"</span></span><span class=\"token punctuation\">></span></span>Red<span class=\"token tag\"><span class=\"token tag\"><span class=\"token punctuation\">&lt;/</span>Button</span><span class=\"token punctuation\">></span></span>\n  <span class=\"token tag\"><span class=\"token tag\"><span class=\"token punctuation\">&lt;</span>Button</span> <span class=\"token attr-name\">outlined</span> <span class=\"token attr-name\">class</span><span class=\"token attr-value\"><span class=\"token punctuation attr-equals\">=</span><span class=\"token punctuation\">\"</span>primary-text<span class=\"token punctuation\">\"</span></span><span class=\"token punctuation\">></span></span>Primary<span class=\"token tag\"><span class=\"token tag\"><span class=\"token punctuation\">&lt;/</span>Button</span><span class=\"token punctuation\">></span></span>\n  <span class=\"token tag\"><span class=\"token tag\"><span class=\"token punctuation\">&lt;</span>Button</span> <span class=\"token attr-name\">outlined</span> <span class=\"token attr-name\">disabled</span><span class=\"token punctuation\">></span></span>Disabled<span class=\"token tag\"><span class=\"token tag\"><span class=\"token punctuation\">&lt;/</span>Button</span><span class=\"token punctuation\">></span></span>\n<span class=\"token tag\"><span class=\"token tag\"><span class=\"token punctuation\">&lt;/</span>div</span><span class=\"token punctuation\">></span></span>\n","path":"examples/components/buttons/outlined.svelte"},"raised":{"code":"<span class=\"token tag\"><span class=\"token tag\"><span class=\"token punctuation\">&lt;</span>script</span><span class=\"token punctuation\">></span></span><span class=\"token script\"><span class=\"token language-javascript\">\n  <span class=\"token keyword\">import</span> Button <span class=\"token keyword\">from</span> <span class=\"token string\">'svelte-materialify/src/components/Button'</span><span class=\"token punctuation\">;</span>\n</span></span><span class=\"token tag\"><span class=\"token tag\"><span class=\"token punctuation\">&lt;/</span>script</span><span class=\"token punctuation\">></span></span>\n\n<span class=\"token tag\"><span class=\"token tag\"><span class=\"token punctuation\">&lt;</span>div</span> <span class=\"token attr-name\">class</span><span class=\"token attr-value\"><span class=\"token punctuation attr-equals\">=</span><span class=\"token punctuation\">\"</span>d-flex flex-column flex-sm-row justify-space-between<span class=\"token punctuation\">\"</span></span><span class=\"token punctuation\">></span></span>\n  <span class=\"token tag\"><span class=\"token tag\"><span class=\"token punctuation\">&lt;</span>Button</span><span class=\"token punctuation\">></span></span>Default<span class=\"token tag\"><span class=\"token tag\"><span class=\"token punctuation\">&lt;/</span>Button</span><span class=\"token punctuation\">></span></span>\n  <span class=\"token tag\"><span class=\"token tag\"><span class=\"token punctuation\">&lt;</span>Button</span> <span class=\"token attr-name\">class</span><span class=\"token attr-value\"><span class=\"token punctuation attr-equals\">=</span><span class=\"token punctuation\">\"</span>red white-text<span class=\"token punctuation\">\"</span></span><span class=\"token punctuation\">></span></span>Red<span class=\"token tag\"><span class=\"token tag\"><span class=\"token punctuation\">&lt;/</span>Button</span><span class=\"token punctuation\">></span></span>\n  <span class=\"token tag\"><span class=\"token tag\"><span class=\"token punctuation\">&lt;</span>Button</span> <span class=\"token attr-name\">class</span><span class=\"token attr-value\"><span class=\"token punctuation attr-equals\">=</span><span class=\"token punctuation\">\"</span>primary-color<span class=\"token punctuation\">\"</span></span><span class=\"token punctuation\">></span></span>Primary<span class=\"token tag\"><span class=\"token tag\"><span class=\"token punctuation\">&lt;/</span>Button</span><span class=\"token punctuation\">></span></span>\n  <span class=\"token tag\"><span class=\"token tag\"><span class=\"token punctuation\">&lt;</span>Button</span> <span class=\"token attr-name\">disabled</span><span class=\"token punctuation\">></span></span>Disabled<span class=\"token tag\"><span class=\"token tag\"><span class=\"token punctuation\">&lt;/</span>Button</span><span class=\"token punctuation\">></span></span>\n<span class=\"token tag\"><span class=\"token tag\"><span class=\"token punctuation\">&lt;/</span>div</span><span class=\"token punctuation\">></span></span>\n","path":"examples/components/buttons/raised.svelte"},"rounded":{"code":"<span class=\"token tag\"><span class=\"token tag\"><span class=\"token punctuation\">&lt;</span>script</span><span class=\"token punctuation\">></span></span><span class=\"token script\"><span class=\"token language-javascript\">\n  <span class=\"token keyword\">import</span> Button <span class=\"token keyword\">from</span> <span class=\"token string\">'svelte-materialify/src/components/Button'</span><span class=\"token punctuation\">;</span>\n</span></span><span class=\"token tag\"><span class=\"token tag\"><span class=\"token punctuation\">&lt;/</span>script</span><span class=\"token punctuation\">></span></span>\n\n<span class=\"token tag\"><span class=\"token tag\"><span class=\"token punctuation\">&lt;</span>Button</span> <span class=\"token attr-name\">rounded</span> <span class=\"token attr-name\">class</span><span class=\"token attr-value\"><span class=\"token punctuation attr-equals\">=</span><span class=\"token punctuation\">\"</span>primary-color<span class=\"token punctuation\">\"</span></span><span class=\"token punctuation\">></span></span>Rounded<span class=\"token tag\"><span class=\"token tag\"><span class=\"token punctuation\">&lt;/</span>Button</span><span class=\"token punctuation\">></span></span>\n","path":"examples/components/buttons/rounded.svelte"},"sizing":{"code":"<span class=\"token tag\"><span class=\"token tag\"><span class=\"token punctuation\">&lt;</span>script</span><span class=\"token punctuation\">></span></span><span class=\"token script\"><span class=\"token language-javascript\">\n  <span class=\"token keyword\">import</span> Button <span class=\"token keyword\">from</span> <span class=\"token string\">'svelte-materialify/src/components/Button'</span><span class=\"token punctuation\">;</span>\n  <span class=\"token keyword\">import</span> Icon <span class=\"token keyword\">from</span> <span class=\"token string\">'svelte-materialify/src/components/Icon'</span><span class=\"token punctuation\">;</span>\n</span></span><span class=\"token tag\"><span class=\"token tag\"><span class=\"token punctuation\">&lt;/</span>script</span><span class=\"token punctuation\">></span></span>\n\n<span class=\"token tag\"><span class=\"token tag\"><span class=\"token punctuation\">&lt;</span>div</span> <span class=\"token attr-name\">class</span><span class=\"token attr-value\"><span class=\"token punctuation attr-equals\">=</span><span class=\"token punctuation\">\"</span>text-center<span class=\"token punctuation\">\"</span></span><span class=\"token punctuation\">></span></span>\n  <span class=\"token tag\"><span class=\"token tag\"><span class=\"token punctuation\">&lt;</span>Button</span> <span class=\"token attr-name\">size</span><span class=\"token attr-value\"><span class=\"token punctuation attr-equals\">=</span><span class=\"token punctuation\">\"</span>x-small<span class=\"token punctuation\">\"</span></span> <span class=\"token attr-name\">class</span><span class=\"token attr-value\"><span class=\"token punctuation attr-equals\">=</span><span class=\"token punctuation\">\"</span>red white-text<span class=\"token punctuation\">\"</span></span><span class=\"token punctuation\">></span></span>x-small<span class=\"token tag\"><span class=\"token tag\"><span class=\"token punctuation\">&lt;/</span>Button</span><span class=\"token punctuation\">></span></span>\n  <span class=\"token tag\"><span class=\"token tag\"><span class=\"token punctuation\">&lt;</span>Button</span> <span class=\"token attr-name\">size</span><span class=\"token attr-value\"><span class=\"token punctuation attr-equals\">=</span><span class=\"token punctuation\">\"</span>small<span class=\"token punctuation\">\"</span></span> <span class=\"token attr-name\">class</span><span class=\"token attr-value\"><span class=\"token punctuation attr-equals\">=</span><span class=\"token punctuation\">\"</span>green white-text<span class=\"token punctuation\">\"</span></span><span class=\"token punctuation\">></span></span>small<span class=\"token tag\"><span class=\"token tag\"><span class=\"token punctuation\">&lt;/</span>Button</span><span class=\"token punctuation\">></span></span>\n  <span class=\"token tag\"><span class=\"token tag\"><span class=\"token punctuation\">&lt;</span>Button</span> <span class=\"token attr-name\">size</span><span class=\"token attr-value\"><span class=\"token punctuation attr-equals\">=</span><span class=\"token punctuation\">\"</span>default<span class=\"token punctuation\">\"</span></span> <span class=\"token attr-name\">class</span><span class=\"token attr-value\"><span class=\"token punctuation attr-equals\">=</span><span class=\"token punctuation\">\"</span>blue white-text<span class=\"token punctuation\">\"</span></span><span class=\"token punctuation\">></span></span>default<span class=\"token tag\"><span class=\"token tag\"><span class=\"token punctuation\">&lt;/</span>Button</span><span class=\"token punctuation\">></span></span>\n  <span class=\"token tag\"><span class=\"token tag\"><span class=\"token punctuation\">&lt;</span>Button</span> <span class=\"token attr-name\">size</span><span class=\"token attr-value\"><span class=\"token punctuation attr-equals\">=</span><span class=\"token punctuation\">\"</span>large<span class=\"token punctuation\">\"</span></span> <span class=\"token attr-name\">class</span><span class=\"token attr-value\"><span class=\"token punctuation attr-equals\">=</span><span class=\"token punctuation\">\"</span>orange white-text<span class=\"token punctuation\">\"</span></span><span class=\"token punctuation\">></span></span>large<span class=\"token tag\"><span class=\"token tag\"><span class=\"token punctuation\">&lt;/</span>Button</span><span class=\"token punctuation\">></span></span>\n  <span class=\"token tag\"><span class=\"token tag\"><span class=\"token punctuation\">&lt;</span>Button</span> <span class=\"token attr-name\">size</span><span class=\"token attr-value\"><span class=\"token punctuation attr-equals\">=</span><span class=\"token punctuation\">\"</span>x-large<span class=\"token punctuation\">\"</span></span> <span class=\"token attr-name\">class</span><span class=\"token attr-value\"><span class=\"token punctuation attr-equals\">=</span><span class=\"token punctuation\">\"</span>indigo white-text<span class=\"token punctuation\">\"</span></span><span class=\"token punctuation\">></span></span>x-large<span class=\"token tag\"><span class=\"token tag\"><span class=\"token punctuation\">&lt;/</span>Button</span><span class=\"token punctuation\">></span></span>\n<span class=\"token tag\"><span class=\"token tag\"><span class=\"token punctuation\">&lt;/</span>div</span><span class=\"token punctuation\">></span></span>\n<span class=\"token tag\"><span class=\"token tag\"><span class=\"token punctuation\">&lt;</span>br</span> <span class=\"token punctuation\">/></span></span>\n<span class=\"token tag\"><span class=\"token tag\"><span class=\"token punctuation\">&lt;</span>div</span> <span class=\"token attr-name\">class</span><span class=\"token attr-value\"><span class=\"token punctuation attr-equals\">=</span><span class=\"token punctuation\">\"</span>text-center<span class=\"token punctuation\">\"</span></span><span class=\"token punctuation\">></span></span>\n  <span class=\"token tag\"><span class=\"token tag\"><span class=\"token punctuation\">&lt;</span>Button</span> <span class=\"token attr-name\">fab</span> <span class=\"token attr-name\">size</span><span class=\"token attr-value\"><span class=\"token punctuation attr-equals\">=</span><span class=\"token punctuation\">\"</span>x-small<span class=\"token punctuation\">\"</span></span> <span class=\"token attr-name\">class</span><span class=\"token attr-value\"><span class=\"token punctuation attr-equals\">=</span><span class=\"token punctuation\">\"</span>red white-text<span class=\"token punctuation\">\"</span></span><span class=\"token punctuation\">></span></span>\n    <span class=\"token tag\"><span class=\"token tag\"><span class=\"token punctuation\">&lt;</span>Icon</span> <span class=\"token attr-name\">size</span><span class=\"token attr-value\"><span class=\"token punctuation attr-equals\">=</span><span class=\"token punctuation\">\"</span>16px<span class=\"token punctuation\">\"</span></span> <span class=\"token attr-name\">class</span><span class=\"token attr-value\"><span class=\"token punctuation attr-equals\">=</span><span class=\"token punctuation\">\"</span>mdi mdi-pen<span class=\"token punctuation\">\"</span></span> <span class=\"token punctuation\">/></span></span>\n  <span class=\"token tag\"><span class=\"token tag\"><span class=\"token punctuation\">&lt;/</span>Button</span><span class=\"token punctuation\">></span></span>\n  <span class=\"token tag\"><span class=\"token tag\"><span class=\"token punctuation\">&lt;</span>Button</span> <span class=\"token attr-name\">fab</span> <span class=\"token attr-name\">size</span><span class=\"token attr-value\"><span class=\"token punctuation attr-equals\">=</span><span class=\"token punctuation\">\"</span>small<span class=\"token punctuation\">\"</span></span> <span class=\"token attr-name\">class</span><span class=\"token attr-value\"><span class=\"token punctuation attr-equals\">=</span><span class=\"token punctuation\">\"</span>green white-text<span class=\"token punctuation\">\"</span></span><span class=\"token punctuation\">></span></span>\n    <span class=\"token tag\"><span class=\"token tag\"><span class=\"token punctuation\">&lt;</span>Icon</span> <span class=\"token attr-name\">class</span><span class=\"token attr-value\"><span class=\"token punctuation attr-equals\">=</span><span class=\"token punctuation\">\"</span>mdi mdi-pen<span class=\"token punctuation\">\"</span></span> <span class=\"token punctuation\">/></span></span>\n  <span class=\"token tag\"><span class=\"token tag\"><span class=\"token punctuation\">&lt;/</span>Button</span><span class=\"token punctuation\">></span></span>\n  <span class=\"token tag\"><span class=\"token tag\"><span class=\"token punctuation\">&lt;</span>Button</span> <span class=\"token attr-name\">fab</span> <span class=\"token attr-name\">size</span><span class=\"token attr-value\"><span class=\"token punctuation attr-equals\">=</span><span class=\"token punctuation\">\"</span>default<span class=\"token punctuation\">\"</span></span> <span class=\"token attr-name\">class</span><span class=\"token attr-value\"><span class=\"token punctuation attr-equals\">=</span><span class=\"token punctuation\">\"</span>blue white-text<span class=\"token punctuation\">\"</span></span><span class=\"token punctuation\">></span></span>\n    <span class=\"token tag\"><span class=\"token tag\"><span class=\"token punctuation\">&lt;</span>Icon</span> <span class=\"token attr-name\">class</span><span class=\"token attr-value\"><span class=\"token punctuation attr-equals\">=</span><span class=\"token punctuation\">\"</span>mdi mdi-pen<span class=\"token punctuation\">\"</span></span> <span class=\"token punctuation\">/></span></span>\n  <span class=\"token tag\"><span class=\"token tag\"><span class=\"token punctuation\">&lt;/</span>Button</span><span class=\"token punctuation\">></span></span>\n  <span class=\"token tag\"><span class=\"token tag\"><span class=\"token punctuation\">&lt;</span>Button</span> <span class=\"token attr-name\">fab</span> <span class=\"token attr-name\">size</span><span class=\"token attr-value\"><span class=\"token punctuation attr-equals\">=</span><span class=\"token punctuation\">\"</span>large<span class=\"token punctuation\">\"</span></span> <span class=\"token attr-name\">class</span><span class=\"token attr-value\"><span class=\"token punctuation attr-equals\">=</span><span class=\"token punctuation\">\"</span>orange white-text<span class=\"token punctuation\">\"</span></span><span class=\"token punctuation\">></span></span>\n    <span class=\"token tag\"><span class=\"token tag\"><span class=\"token punctuation\">&lt;</span>Icon</span> <span class=\"token attr-name\">class</span><span class=\"token attr-value\"><span class=\"token punctuation attr-equals\">=</span><span class=\"token punctuation\">\"</span>mdi mdi-pen<span class=\"token punctuation\">\"</span></span> <span class=\"token punctuation\">/></span></span>\n  <span class=\"token tag\"><span class=\"token tag\"><span class=\"token punctuation\">&lt;/</span>Button</span><span class=\"token punctuation\">></span></span>\n  <span class=\"token tag\"><span class=\"token tag\"><span class=\"token punctuation\">&lt;</span>Button</span> <span class=\"token attr-name\">fab</span> <span class=\"token attr-name\">size</span><span class=\"token attr-value\"><span class=\"token punctuation attr-equals\">=</span><span class=\"token punctuation\">\"</span>x-large<span class=\"token punctuation\">\"</span></span> <span class=\"token attr-name\">class</span><span class=\"token attr-value\"><span class=\"token punctuation attr-equals\">=</span><span class=\"token punctuation\">\"</span>indigo white-text<span class=\"token punctuation\">\"</span></span><span class=\"token punctuation\">></span></span>\n    <span class=\"token tag\"><span class=\"token tag\"><span class=\"token punctuation\">&lt;</span>Icon</span> <span class=\"token attr-name\">size</span><span class=\"token attr-value\"><span class=\"token punctuation attr-equals\">=</span><span class=\"token punctuation\">\"</span>28px<span class=\"token punctuation\">\"</span></span> <span class=\"token attr-name\">class</span><span class=\"token attr-value\"><span class=\"token punctuation attr-equals\">=</span><span class=\"token punctuation\">\"</span>mdi mdi-pen<span class=\"token punctuation\">\"</span></span> <span class=\"token punctuation\">/></span></span>\n  <span class=\"token tag\"><span class=\"token tag\"><span class=\"token punctuation\">&lt;/</span>Button</span><span class=\"token punctuation\">></span></span>\n<span class=\"token tag\"><span class=\"token tag\"><span class=\"token punctuation\">&lt;/</span>div</span><span class=\"token punctuation\">></span></span>\n","path":"examples/components/buttons/sizing.svelte"},"text":{"code":"<span class=\"token tag\"><span class=\"token tag\"><span class=\"token punctuation\">&lt;</span>script</span><span class=\"token punctuation\">></span></span><span class=\"token script\"><span class=\"token language-javascript\">\n  <span class=\"token keyword\">import</span> Button <span class=\"token keyword\">from</span> <span class=\"token string\">'svelte-materialify/src/components/Button'</span><span class=\"token punctuation\">;</span>\n</span></span><span class=\"token tag\"><span class=\"token tag\"><span class=\"token punctuation\">&lt;/</span>script</span><span class=\"token punctuation\">></span></span>\n\n<span class=\"token tag\"><span class=\"token tag\"><span class=\"token punctuation\">&lt;</span>div</span> <span class=\"token attr-name\">class</span><span class=\"token attr-value\"><span class=\"token punctuation attr-equals\">=</span><span class=\"token punctuation\">\"</span>d-flex flex-column flex-sm-row justify-space-between<span class=\"token punctuation\">\"</span></span><span class=\"token punctuation\">></span></span>\n  <span class=\"token tag\"><span class=\"token tag\"><span class=\"token punctuation\">&lt;</span>Button</span> <span class=\"token attr-name\">text</span><span class=\"token punctuation\">></span></span>Default<span class=\"token tag\"><span class=\"token tag\"><span class=\"token punctuation\">&lt;/</span>Button</span><span class=\"token punctuation\">></span></span>\n  <span class=\"token tag\"><span class=\"token tag\"><span class=\"token punctuation\">&lt;</span>Button</span> <span class=\"token attr-name\">text</span> <span class=\"token attr-name\">class</span><span class=\"token attr-value\"><span class=\"token punctuation attr-equals\">=</span><span class=\"token punctuation\">\"</span>red-text<span class=\"token punctuation\">\"</span></span><span class=\"token punctuation\">></span></span>Red<span class=\"token tag\"><span class=\"token tag\"><span class=\"token punctuation\">&lt;/</span>Button</span><span class=\"token punctuation\">></span></span>\n  <span class=\"token tag\"><span class=\"token tag\"><span class=\"token punctuation\">&lt;</span>Button</span> <span class=\"token attr-name\">text</span> <span class=\"token attr-name\">class</span><span class=\"token attr-value\"><span class=\"token punctuation attr-equals\">=</span><span class=\"token punctuation\">\"</span>primary-text<span class=\"token punctuation\">\"</span></span><span class=\"token punctuation\">></span></span>Primary<span class=\"token tag\"><span class=\"token tag\"><span class=\"token punctuation\">&lt;/</span>Button</span><span class=\"token punctuation\">></span></span>\n  <span class=\"token tag\"><span class=\"token tag\"><span class=\"token punctuation\">&lt;</span>Button</span> <span class=\"token attr-name\">text</span> <span class=\"token attr-name\">disabled</span><span class=\"token punctuation\">></span></span>Disabled<span class=\"token tag\"><span class=\"token tag\"><span class=\"token punctuation\">&lt;/</span>Button</span><span class=\"token punctuation\">></span></span>\n<span class=\"token tag\"><span class=\"token tag\"><span class=\"token punctuation\">&lt;/</span>div</span><span class=\"token punctuation\">></span></span>\n","path":"examples/components/buttons/text.svelte"},"tile":{"code":"<span class=\"token tag\"><span class=\"token tag\"><span class=\"token punctuation\">&lt;</span>script</span><span class=\"token punctuation\">></span></span><span class=\"token script\"><span class=\"token language-javascript\">\n  <span class=\"token keyword\">import</span> Button <span class=\"token keyword\">from</span> <span class=\"token string\">'svelte-materialify/src/components/Button'</span><span class=\"token punctuation\">;</span>\n  <span class=\"token keyword\">import</span> Icon <span class=\"token keyword\">from</span> <span class=\"token string\">'svelte-materialify/src/components/Icon'</span><span class=\"token punctuation\">;</span>\n</span></span><span class=\"token tag\"><span class=\"token tag\"><span class=\"token punctuation\">&lt;/</span>script</span><span class=\"token punctuation\">></span></span>\n\n<span class=\"token tag\"><span class=\"token tag\"><span class=\"token punctuation\">&lt;</span>div</span> <span class=\"token attr-name\">class</span><span class=\"token attr-value\"><span class=\"token punctuation attr-equals\">=</span><span class=\"token punctuation\">\"</span>text-center<span class=\"token punctuation\">\"</span></span><span class=\"token punctuation\">></span></span>\n  <span class=\"token tag\"><span class=\"token tag\"><span class=\"token punctuation\">&lt;</span>Button</span> <span class=\"token attr-name\">tile</span> <span class=\"token attr-name\">class</span><span class=\"token attr-value\"><span class=\"token punctuation attr-equals\">=</span><span class=\"token punctuation\">\"</span>indigo white-text<span class=\"token punctuation\">\"</span></span><span class=\"token punctuation\">></span></span>\n    <span class=\"token tag\"><span class=\"token tag\"><span class=\"token punctuation\">&lt;</span>Icon</span> <span class=\"token attr-name\">class</span><span class=\"token attr-value\"><span class=\"token punctuation attr-equals\">=</span><span class=\"token punctuation\">\"</span>mdi mdi-pen mr-3<span class=\"token punctuation\">\"</span></span> <span class=\"token punctuation\">/></span></span>\n    Tile\n  <span class=\"token tag\"><span class=\"token tag\"><span class=\"token punctuation\">&lt;/</span>Button</span><span class=\"token punctuation\">></span></span>\n<span class=\"token tag\"><span class=\"token tag\"><span class=\"token punctuation\">&lt;/</span>div</span><span class=\"token punctuation\">></span></span>\n","path":"examples/components/buttons/tile.svelte"}}